<?xml version="1.0" encoding="UTF-8"?>
<GenRun Id="cdc_fifo_gen_synth_1" LaunchPart="xc7a100tcsg324-1" LaunchTime="1461610006">
  <File Type="RDS-DCP" Name="cdc_fifo_gen.dcp"/>
  <File Type="RUN-CONSTRS" Name="$PDATADIR/runs/cdc_fifo_gen_synth_1/constrs_in.xml"/>
  <File Type="RDS-UTIL-PB" Name="cdc_fifo_gen_utilization_synth.pb"/>
  <File Type="RUN-SRCS" Name="$PDATADIR/runs/cdc_fifo_gen_synth_1/sources.xml"/>
  <File Type="RDS-PROPCONSTRS" Name="cdc_fifo_gen_drc_synth.rpt"/>
  <File Type="PA-TCL" Name="cdc_fifo_gen.tcl"/>
  <File Type="RUN-STRAT" Name="$PDATADIR/runs/cdc_fifo_gen_synth_1/cdc_fifo_gen_synth_1.psg"/>
  <File Type="RDS-RDS" Name="cdc_fifo_gen.vds"/>
  <File Type="RDS-UTIL" Name="cdc_fifo_gen_utilization_synth.rpt"/>
  <File Type="VDS-TIMINGSUMMARY" Name="cdc_fifo_gen_timing_summary_synth.rpt"/>
  <File Type="VDS-TIMING-PB" Name="cdc_fifo_gen_timing_summary_synth.pb"/>
  <FileSet Name="sources" Type="BlockSrcs" RelSrcDir="$PSRCDIR/cdc_fifo_gen">
    <File Path="$PSRCDIR/sources_1/ip/cdc_fifo_gen/cdc_fifo_gen.xci">
      <FileInfo>
        <Attr Name="UsedIn" Val="synthesis"/>
        <Attr Name="UsedIn" Val="implementation"/>
        <Attr Name="UsedIn" Val="simulation"/>
      </FileInfo>
    </File>
    <Config>
      <Option Name="TopModule" Val="cdc_fifo_gen"/>
      <Option Name="UseBlackboxStub" Val="1"/>
    </Config>
  </FileSet>
  <FileSet Name="constrs_in" Type="BlockSrcs" RelSrcDir="$PSRCDIR/cdc_fifo_gen">
    <File Path="$PSRCDIR/sources_1/ip/cdc_fifo_gen/cdc_fifo_gen.xci">
      <FileInfo>
        <Attr Name="UsedIn" Val="synthesis"/>
        <Attr Name="UsedIn" Val="implementation"/>
        <Attr Name="UsedIn" Val="simulation"/>
      </FileInfo>
    </File>
    <Config>
      <Option Name="TopModule" Val="cdc_fifo_gen"/>
      <Option Name="UseBlackboxStub" Val="1"/>
    </Config>
  </FileSet>
  <Strategy Version="1" Minor="2">
    <StratHandle Name="Vivado Synthesis Defaults" Flow="Vivado Synthesis 2015">
      <Desc>Vivado Synthesis Defaults</Desc>
    </StratHandle>
    <Step Id="synth_design"/>
  </Strategy>
</GenRun>
